README.md
setup.py
nicotool/__init__.py
nicotool/additional_functions.py
nicotool/api_request.py
nicotool/ascii.py
nicotool/colors.py
nicotool/data_manipulation.py
nicotool/database.py
nicotool/files.py
nicotool/id.py
nicotool/jsonify.py
nicotool/keyboard.py
nicotool/print_additions.py
nicotool/profanities.py
nicotool/youtube.py
nicotool.egg-info/PKG-INFO
nicotool.egg-info/SOURCES.txt
nicotool.egg-info/dependency_links.txt
nicotool.egg-info/requires.txt
nicotool.egg-info/top_level.txt