Metadata-Version: 2.1
Name: nicotool
Version: 1.4.8.6
Summary: A handy litle tool
Home-page: UNKNOWN
Author: Nico
License: UNKNOWN
Platform: UNKNOWN
